toml_file/__init__.py
toml_file/config.py
toml_file/encoder.py
toml_file/parser.py
toml_file/types.py
toml_file-1.0.8.dist-info/METADATA
toml_file-1.0.8.dist-info/WHEEL
toml_file-1.0.8.dist-info/top_level.txt
toml_file-1.0.8.dist-info/RECORD
