Metadata-Version: 2.1
Name: toml_file
Version: 1.0.8
Summary: TOML file reader - python module to read/write toml configuration files
Home-page: https://gitlab.com/tcharrett/toml_file
Author: Tom Charrett
Author-email: tcharrett@gmail.com
Classifier: Programming Language :: Python :: 3
Classifier: License :: OSI Approved :: GNU General Public License (GPL)
Classifier: Topic :: Scientific/Engineering
Classifier: Topic :: Text Processing
